Metadata-Version: 1.0
Name: Bigeleisen-KIE
Version: 1.0
Summary: library which provides tools capable of calculating the Kinetic Isotope Effect according to the Bigeleisen equation
Home-page: https://github.com/valkenzz/Bigeleisen_KIE
Author: Valkenzz
Author-email: valentin.meo.1@ulaval.ca
License: UNKNOWN
Platform: UNKNOWN
